Workbook

Sheet Property List
A1: Bridge Industrial Properties – Consolidated Property List
A4: S.NO | B4: Property | C4: Address | D4: City | E4: State | F4: Building GLA (sq ft)
A5: 1 | B5: Kurv Melrose Park | C5: 10400 W North Ave | D5: Melrose Park | E5: IL | F5: 1557680
A6: 2 | B6: Kurv McCook | C6: 9301 W 55th St | D6: McCook | E6: IL | F6: 1193232
A7: 3 | B7: Kurv Fountain Square | C7: 640 Remington Blvd | D7: Bolingbrook | E7: IL | F7: 965751
A8: 4 | B8: Kurv Romeoville | C8: 295 & 351 Southcreek Pkwy | D8: Romeoville | E8: IL | F8: 658886
A9: 5 | B9: Kurv Wood Dale | C9: 700 N Wood Dale Rd | D9: Wood Dale | E9: IL | F9: 340579
A10: 6 | B10: Kurv Summit | C10: 7955 W 59th St | D10: Summit | E10: IL | F10: 362283
A11: 7 | B11: Kurv Mundelein | C11: 290 Townline Rd | D11: Mundelein | E11: IL | F11: 321024
A12: 8 | B12: Kurv Route 53 | C12: 755-757 Independence Blvd | D12: Romeoville | E12: IL | F12: 292053
A13: 9 | B13: Kurv Itasca | C13: 1055 W Devon Ave | D13: Itasca | E13: IL | F13: 246388
A14: 10 | B14: Kurv Downers Grove IV | C14: 2300 Warrenville Rd | D14: Downers Grove | E14: IL | F14: 245117
A15: 11 | B15: Kurv Melrose Park II | C15: 2100 N 15th Ave | D15: Melrose Park | E15: IL | F15: 187596
A16: 12 | B16: Kurv Skokie | C16: 7800 Austin Ave | D16: Skokie | E16: IL | F16: 171822
... A35: 31 | B35: Kurv West Linden | C35: 525 West Linden Ave | D35: Linden | E35: NJ | F35: 114910
B37: Total | F37: =SUM(F5:F36) -> 13711249

Sheet Valuation
A1: Property | B1: City | C1: State | D1: Building GLA (sq ft) | E1: System Size (kW) | F1: Region | G1: Lease Rate ($/kW) | H1: Solar Revenue - High ($) | I1: Solar Revenue - Low ($) | J1: Solar Revenue - Midpoint ($) | K1: BESS Eligible? | L1: Bess Revenue ($) | M1: Total NOI - Midpoint ($)
A2: Kurv Melrose Park | B2: Melrose Park | C2: IL | D2: 1557680 | E2: =D2/100 -> 15576.8 | F2: IL | G2: {=IFERROR(INDEX($D$60:$F$74, MATCH(TRIM(F2),$C$60:$C$74,0), IF(E2>2000,2,IF(E2>=1000,1,3))), "Check region")} -> 45 | H2: =ROUND(E2*G2,-3) -> 701000 | I2: =ROUND(H2*0.75,-3) -> 526000 | J2: =AVERAGE(H2:I2) -> 613500 | K2: Yes | L2: =IF(K2="Yes",$D$75,0) -> 100000 | M2: =J2+L2 -> 713500
A3: Kurv McCook | B3: McCook | C3: IL | D3: 1193232 | E3: =D3/100 -> 11932.32 | F3: IL | G3: {=IFERROR(INDEX($D$60:$F$74, MATCH(TRIM(F3),$C$60:$C$74,0), IF(E3>2000,2,IF(E3>=1000,1,3))), "Check region")} -> 45 | H3: =ROUND(E3*G3,-3) -> 537000 | I3: =ROUND(H3*0.75,-3) -> 403000 | J3: =AVERAGE(H3:I3) -> 470000 | K3: Yes | L3: =IF(K3="Yes",$D$75,0) -> 100000 | M3: =J3+L3 -> 570000
A4: Kurv Fountain Square | B4: Bolingbrook | C4: IL | D4: 965751 | E4: =D4/100 -> 9657.51 | F4: IL | G4: {=IFERROR(INDEX($D$60:$F$74, MATCH(TRIM(F4),$C$60:$C$74,0), IF(E4>2000,2,IF(E4>=1000,1,3))), "Check region")} -> 45 | H4: =ROUND(E4*G4,-3) -> 435000 | I4: =ROUND(H4*0.75,-3) -> 326000 | J4: =AVERAGE(H4:I4) -> 380500 | K4: Yes | L4: =IF(K4="Yes",$D$75,0) -> 100000 | M4: =J4+L4 -> 480500
A5: Kurv Romeoville | B5: Romeoville | C5: IL | D5: 658886 | E5: =D5/100 -> 6588.86 | F5: IL | G5: {=IFERROR(INDEX($D$60:$F$74, MATCH(TRIM(F5),$C$60:$C$74,0), IF(E5>2000,2,IF(E5>=1000,1,3))), "Check region")} -> 45 | H5: =ROUND(E5*G5,-3) -> 296000 | I5: =ROUND(H5*0.75,-3) -> 222000 | J5: =AVERAGE(H5:I5) -> 259000 | K5: Yes | L5: =IF(K5="Yes",$D$75,0) -> 100000 | M5: =J5+L5 -> 359000
A6: Kurv Wood Dale | B6: Wood Dale | C6: IL | D6: 340579 | E6: =D6/100 -> 3405.79 | F6: IL | G6: {=IFERROR(INDEX($D$60:$F$74, MATCH(TRIM(F6),$C$60:$C$74,0), IF(E6>2000,2,IF(E6>=1000,1,3))), "Check region")} -> 45 | H6: =ROUND(E6*G6,-3) -> 153000 | I6: =ROUND(H6*0.75,-3) -> 115000 | J6: =AVERAGE(H6:I6) -> 134000 | K6: Yes | L6: =IF(K6="Yes",$D$75,0) -> 100000 | M6: =J6+L6 -> 234000
A7: Kurv Summit | B7: Summit | C7: IL | D7: 362283 | E7: =D7/100 -> 3622.83 | F7: IL | G7: {=IFERROR(INDEX($D$60:$F$74, MATCH(TRIM(F7),$C$60:$C$74,0), IF(E7>2000,2,IF(E7>=1000,1,3))), "Check region")} -> 45 | H7: =ROUND(E7*G7,-3) -> 163000 | I7: =ROUND(H7*0.75,-3) -> 122000 | J7: =AVERAGE(H7:I7) -> 142500 | K7: Yes | L7: =IF(K7="Yes",$D$75,0) -> 100000 | M7: =J7+L7 -> 242500
A8: Kurv Mundelein | B8: Mundelein | C8: IL | D8: 321024 | E8: =D8/100 -> 3210.24 | F8: IL | G8: {=IFERROR(INDEX($D$60:$F$74, MATCH(TRIM(F8),$C$60:$C$74,0), IF(E8>2000,2,IF(E8>=1000,1,3))), "Check region")} -> 45 | H8: =ROUND(E8*G8,-3) -> 144000 | I8: =ROUND(H8*0.75,-3) -> 108000 | J8: =AVERAGE(H8:I8) -> 126000 | K8: Yes | L8: =IF(K8="Yes",$D$75,0) -> 100000 | M8: =J8+L8 -> 226000
A9: Kurv Route 53 | B9: Romeoville | C9: IL | D9: 292053 | E9: =D9/100 -> 2920.53 | F9: IL | G9: {=IFERROR(INDEX($D$60:$F$74, MATCH(TRIM(F9),$C$60:$C$74,0), IF(E9>2000,2,IF(E9>=1000,1,3))), "Check region")} -> 45 | H9: =ROUND(E9*G9,-3) -> 131000 | I9: =ROUND(H9*0.75,-3) -> 98000 | J9: =AVERAGE(H9:I9) -> 114500 | K9: Yes | L9: =IF(K9="Yes",$D$75,0) -> 100000 | M9: =J9+L9 -> 214500
A10: Kurv Itasca | B10: Itasca | C10: IL | D10: 246388 | E10: =D10/100 -> 2463.88 | F10: IL | G10: {=IFERROR(INDEX($D$60:$F$74, MATCH(TRIM(F10),$C$60:$C$74,0), IF(E10>2000,2,IF(E10>=1000,1,3))), "Check region")} -> 45 | H10: =ROUND(E10*G10,-3) -> 111000 | I10: =ROUND(H10*0.75,-3) -> 83000 | J10: =AVERAGE(H10:I10) -> 97000 | K10: Yes | L10: =IF(K10="Yes",$D$75,0) -> 100000 | M10: =J10+L10 -> 197000
A11: Kurv Downers Grove IV | B11: Downers Grove | C11: IL | D11: 245117 | E11: =D11/100 -> 2451.17 | F11: IL | G11: {=IFERROR(INDEX($D$60:$F$74, MATCH(TRIM(F11),$C$60:$C$74,0), IF(E11>2000,2,IF(E11>=1000,1,3))), "Check region")} -> 45 | H11: =ROUND(E11*G11,-3) -> 110000 | I11: =ROUND(H11*0.75,-3) -> 83000 | J11: =AVERAGE(H11:I11) -> 96500 | K11: Yes | L11: =IF(K11="Yes",$D$75,0) -> 100000 | M11: =J11+L11 -> 196500
A12: Kurv Melrose Park II | B12: Melrose Park | C12: IL | D12: 187596 | E12: =D12/100 -> 1875.96 | F12: IL | G12: {=IFERROR(INDEX($D$60:$F$74, MATCH(TRIM(F12),$C$60:$C$74,0), IF(E12>2000,2,IF(E12>=1000,1,3))), "Check region")} -> 40 | H12: =ROUND(E12*G12,-3) -> 75000 | I12: =ROUND(H12*0.75,-3) -> 56000 | J12: =AVERAGE(H12:I12) -> 65500 | K12: Yes | L12: =IF(K12="Yes",$D$75,0) -> 100000 | M12: =J12+L12 -> 165500
A13: Kurv Skokie | B13: Skokie | C13: IL | D13: 171822 | E13: =D13/100 -> 1718.22 | F13: IL | G13: {=IFERROR(INDEX($D$60:$F$74, MATCH(TRIM(F13),$C$60:$C$74,0), IF(E13>2000,2,IF(E13>=1000,1,3))), "Check region")} -> 40 | H13: =ROUND(E13*G13,-3) -> 69000 | I13: =ROUND(H13*0.75,-3) -> 52000 | J13: =AVERAGE(H13:I13) -> 60500 | K13: Yes | L13: =IF(K13="Yes",$D$75,0) -> 100000 | M13: =J13+L13 -> 160500
... A32: Kurv West Linden | B32: Linden | C32: NJ | D32: 114910 | E32: =D32/100 -> 1149.1 | F32: NJ - PSE&G | G32: {=IFERROR(INDEX($D$60:$F$74, MATCH(TRIM(F32),$C$60:$C$74,0), IF(E32>2000,2,IF(E32>=1000,1,3))), "Check region")} -> 100 | H32: =ROUND(E32*G32,-3) -> 115000 | I32: =ROUND(H32*0.75,-3) -> 86000 | J32: =AVERAGE(H32:I32) -> 100500 | K32: Yes | L32: =IF(K32="Yes",$D$75,0) -> 100000 | M32: =J32+L32 -> 200500
A34: Total | D34: =SUM(D2:D33) -> 13711249 | E34: =SUM(E2:E33) -> 137112.49 | H34: =SUM(H2:H33) -> 9787000 | I34: =SUM(I2:I33) -> 7343000 | J34: =SUM(J2:J33) -> 8565000 | L34: =SUM(L2:L33) -> 3100000 | M34: =SUM(M2:M33) -> 11665000
C59: Region | D59: 1,000-2,000 kW ($/kW) | E59: Over 2,000 kW ($/kW) | F59: 500-1,000 kW ($/kW) | G59: Cap Rate | H59: Asset Value
C60: NY - Upstate | D60: 0 | E60: 0 | F60: 0 | G60: 0.05 | H60: =$M$34/G60 -> 233300000
C61: NJ - JCP&L | D61: 60 | E61: 70 | F61: 50 | G61: 0.055 | H61: =$M$34/G61 -> 2.1209091e+08
C62: NY - Westchester | D62: 60 | E62: 60 | F62: 60 | G62: 0.06 | H62: =$M$34/G62 -> 1.9441667e+08
C63: MD | D63: 50 | E63: 60 | F63: 40 | G63: 0.065 | H63: =$M$34/G63 -> 1.7946154e+08
C64: MA - Eversource West | D64: 80 | E64: 80 | F64: 80 | G64: 0.07 | H64: =$M$34/G64 -> 1.6664286e+08
C65: MA - Eversource East | D65: 80 | E65: 80 | F65: 90
C66: NY - NYC | D66: 60 | E66: 60 | F66: 50
C67: NJ - PSE&G | D67: 100 | E67: 110 | F67: 80
C68: MA - National Grid | D68: 80 | E68: 80 | F68: 90
C69: NY - Long Island | D69: 20 | E69: 20 | F69: 15
C70: NJ - ACE | D70: 100 | E70: 110 | F70: 80
C71: IL | D71: 40 | E71: 45 | F71: 40
C72: CA - North | D72: 0 | E72: 0 | F72: 0
C73: CA - South | D73: 0 | E73: 0 | F73: 0
C74: CA - LADWP | D74: 60 | E74: 70 | F74: 50
C75: BESS lease per eligible site | D75: 100000

Sheet Client One-Pager
B2: Bridge Industrial Properties (Kruv) | I2: CLIENT LOGO
B3: Renewable Energy Asset Value Opportunity
B5: ESTIMATED POTENTIAL ASSET-VALUE INCREASE | I5: Client name | J5: Bridge Industrial Properties
B6: =G43/$J$6 -> 1.9441667e+08 | I6: Cap rate | J6: 0.06
I7: BESS lease / eligible site | J7: =Valuation!D75 -> 100000
B10: PROPERTY FOOTPRINT + ANNUAL VALUE | I10: ASSET VALUE AT CAP RATES
B11: Property | C11: State | D11: GLA (sq ft) | E11: Solar Annual Value | F11: BESS Annual Value | G11: Combined Annual Value | I11: Cap Rate | J11: Asset Value
B12: =Valuation!A2 -> Kurv Melrose Park | C12: =Valuation!C2 -> IL | D12: =Valuation!D2 -> 1557680 | E12: =Valuation!J2 -> 613500 | F12: =IF(Valuation!K2="Yes",$J$7,0) -> 100000 | G12: =E12+F12 -> 713500 | I12: 0.05 | J12: =$G$43/I12 -> 233300000
B13: =Valuation!A3 -> Kurv McCook | C13: =Valuation!C3 -> IL | D13: =Valuation!D3 -> 1193232 | E13: =Valuation!J3 -> 470000 | F13: =IF(Valuation!K3="Yes",$J$7,0) -> 100000 | G13: =E13+F13 -> 570000 | I13: 0.055 | J13: =$G$43/I13 -> 2.1209091e+08
B14: =Valuation!A4 -> Kurv Fountain Square | C14: =Valuation!C4 -> IL | D14: =Valuation!D4 -> 965751 | E14: =Valuation!J4 -> 380500 | F14: =IF(Valuation!K4="Yes",$J$7,0) -> 100000 | G14: =E14+F14 -> 480500 | I14: 0.06 | J14: =$G$43/I14 -> 1.9441667e+08
B15: =Valuation!A5 -> Kurv Romeoville | C15: =Valuation!C5 -> IL | D15: =Valuation!D5 -> 658886 | E15: =Valuation!J5 -> 259000 | F15: =IF(Valuation!K5="Yes",$J$7,0) -> 100000 | G15: =E15+F15 -> 359000 | I15: 0.065 | J15: =$G$43/I15 -> 1.7946154e+08
B16: =Valuation!A6 -> Kurv Wood Dale | C16: =Valuation!C6 -> IL | D16: =Valuation!D6 -> 340579 | E16: =Valuation!J6 -> 134000 | F16: =IF(Valuation!K6="Yes",$J$7,0) -> 100000 | G16: =E16+F16 -> 234000 | I16: 0.07 | J16: =$G$43/I16 -> 1.6664286e+08
B17: =Valuation!A7 -> Kurv Summit | C17: =Valuation!C7 -> IL | D17: =Valuation!D7 -> 362283 | E17: =Valuation!J7 -> 142500 | F17: =IF(Valuation!K7="Yes",$J$7,0) -> 100000 | G17: =E17+F17 -> 242500
B18: =Valuation!A8 -> Kurv Mundelein | C18: =Valuation!C8 -> IL | D18: =Valuation!D8 -> 321024 | E18: =Valuation!J8 -> 126000 | F18: =IF(Valuation!K8="Yes",$J$7,0) -> 100000 | G18: =E18+F18 -> 226000
B19: =Valuation!A9 -> Kurv Route 53 | C19: =Valuation!C9 -> IL | D19: =Valuation!D9 -> 292053 | E19: =Valuation!J9 -> 114500 | F19: =IF(Valuation!K9="Yes",$J$7,0) -> 100000 | G19: =E19+F19 -> 214500
B20: =Valuation!A10 -> Kurv Itasca | C20: =Valuation!C10 -> IL | D20: =Valuation!D10 -> 246388 | E20: =Valuation!J10 -> 97000 | F20: =IF(Valuation!K10="Yes",$J$7,0) -> 100000 | G20: =E20+F20 -> 197000
B21: =Valuation!A11 -> Kurv Downers Grove IV | C21: =Valuation!C11 -> IL | D21: =Valuation!D11 -> 245117 | E21: =Valuation!J11 -> 96500 | F21: =IF(Valuation!K11="Yes",$J$7,0) -> 100000 | G21: =E21+F21 -> 196500
B22: =Valuation!A12 -> Kurv Melrose Park II | C22: =Valuation!C12 -> IL | D22: =Valuation!D12 -> 187596 | E22: =Valuation!J12 -> 65500 | F22: =IF(Valuation!K12="Yes",$J$7,0) -> 100000 | G22: =E22+F22 -> 165500
B23: =Valuation!A13 -> Kurv Skokie | C23: =Valuation!C13 -> IL | D23: =Valuation!D13 -> 171822 | E23: =Valuation!J13 -> 60500 | F23: =IF(Valuation!K13="Yes",$J$7,0) -> 100000 | G23: =E23+F23 -> 160500
B24: =Valuation!A14 -> Kurv Bloomingdale | C24: =Valuation!C14 -> IL | D24: =Valuation!D14 -> 172866 | E24: =Valuation!J14 -> 60500 | F24: =IF(Valuation!K14="Yes",$J$7,0) -> 100000 | G24: =E24+F24 -> 160500
B25: =Valuation!A15 -> Kurv Bedford Park II | C25: =Valuation!C15 -> IL | D25: =Valuation!D15 -> 140011 | E25: =Valuation!J15 -> 49000 | F25: =IF(Valuation!K15="Yes",$J$7,0) -> 100000 | G25: =E25+F25 -> 149000
B26: =Valuation!A16 -> Kurv Downers Grove III | C26: =Valuation!C16 -> IL | D26: =Valuation!D16 -> 127665 | E26: =Valuation!J16 -> 44500 | F26: =IF(Valuation!K16="Yes",$J$7,0) -> 100000 | G26: =E26+F26 -> 144500
B27: =Valuation!A17 -> Kurv Bridge Point 78 Phase II | C27: =Valuation!C17 -> NJ | D27: =Valuation!D17 -> 1235513 | E27: =Valuation!J17 -> 757000 | F27: =IF(Valuation!K17="Yes",$J$7,0) -> 100000 | G27: =E27+F27 -> 857000
B28: =Valuation!A18 -> Kurv Somerset | C28: =Valuation!C18 -> NJ | D28: =Valuation!D18 -> 1243982 | E28: =Valuation!J18 -> 1197000 | F28: =IF(Valuation!K18="Yes",$J$7,0) -> 100000 | G28: =E28+F28 -> 1297000
... B42: =Valuation!A32 -> Kurv West Linden | C42: =Valuation!C32 -> NJ | D42: =Valuation!D32 -> 114910 | E42: =Valuation!J32 -> 100500 | F42: =IF(Valuation!K32="Yes",$J$7,0) -> 100000 | G42: =E42+F42 -> 200500
B43: PORTFOLIO TOTAL | D43: =SUM(D12:D42) -> 13711249 | E43: =SUM(E12:E42) -> 8565000 | F43: =SUM(F12:F42) -> 3100000 | G43: =SUM(G12:G42) -> 11665000
B45: VALUE BUILD-UP
B46: 25-Year Solar Value | D46: + | E46: 25-Year BESS Value | G46: Total | I46: Term | J46: 25 years
B47: =SUM(E12:E42)*25 -> 214125000 | D47: =SUM(F12:F42)*25 -> 77500000 | F47: =SUM(B47:E47) -> 291625000 | G47: =SUM(G12:G42)*25 -> 291625000
I48: Cap Rate | J48: =$J$6 -> 0.06
B49: 25-year lease value shown as nominal annual lease income × 25; asset-value estimate remains annual renewable-energy NOI ÷ cap rate. | I49: Asset Value | J49: =SUM(G12:G42)/$J$6 -> 1.9441667e+08
B51: Preliminary screening estimates for discussion purposes only. Solar values reflect midpoint estimates from SolarKal's current market model, with system size estimated at one kW per 100 sq ft of building GLA; usable roof area is subject to site confirmation. BESS assumes $100,000/year for each site identified as eligible, over a 25-year term with no replacement cost modeled. Asset value is annual renewable-energy NOI divided by a 6.0% cap rate. Actual economics depend on site conditions, interconnection, market rules, incentives, lease structure and final diligence
